setup.cfg
setup.py
django_dbfs/__init__.py
django_dbfs/file.py
django_dbfs/fs.py
django_dbfs/models.py
django_dbfs/utils.py
django_dbfs.egg-info/PKG-INFO
django_dbfs.egg-info/SOURCES.txt
django_dbfs.egg-info/dependency_links.txt
django_dbfs.egg-info/requires.txt
django_dbfs.egg-info/top_level.txt
django_dbfs/management/__init__.py
django_dbfs/management/commands/__init__.py
django_dbfs/management/commands/dbfs.py
django_dbfs/migrations/0001_initial.py
django_dbfs/migrations/__init__.py
tests/__init__.py
tests/settings.py